src/__init__.py
src/data_processing/__init__.py
src/data_processing/base.py
src/data_processing/cdr/__init__.py
src/data_processing/cdr/cleaner.py
src/data_processing/cdr/load.py
src/data_processing/cdr/orchestator.py
src/data_processing/create_sqlite_db.py
src/data_processing/data_models.py
src/data_processing/frs_api_queries.py
src/data_processing/main.py
src/data_processing/naics_api_queries.py
src/data_processing/tri/__init__.py
src/data_processing/tri/load/__init__.py
src/data_processing/tri/load/load.py
src/data_processing/tri/orchestator.py
src/data_processing/tri/transform/__init__.py
src/data_processing/tri/transform/base.py
src/data_processing/tri/transform/file_1a.py
src/data_processing/tri/transform/file_1b.py
src/data_processing/tri/transform/file_3a.py
src/data_processing/tri/transform/file_3c.py
src/data_processing/tri/utils.py
src/stat_distribution/__init__.py
src/stat_distribution/db_queries.py
src/stat_distribution/dist_generator.py
focapd-0.1.9.dist-info/LICENSE
focapd-0.1.9.dist-info/METADATA
focapd-0.1.9.dist-info/WHEEL
focapd-0.1.9.dist-info/RECORD
